llm_feat/__init__.py
llm_feat/core.py
llm_feat/jupyter_utils.py
llm_feat/llm_client.py
llm_feat/version.py
llm_feat-0.2.3.dist-info/LICENSE
llm_feat-0.2.3.dist-info/METADATA
llm_feat-0.2.3.dist-info/WHEEL
llm_feat-0.2.3.dist-info/RECORD
