Metadata-Version: 2.1
Name: llm-feat
Version: 0.2.3
Summary: Automated feature engineering using Large Language Models (LLMs) for tabular data
Home-page: https://github.com/codeastra2/llm-feat
License: MIT
Keywords: machine-learning,feature-engineering,llm,openai,pandas,data-science
Author: Srinivas Kumar
Author-email: srinivas1996kumar@gmail.com
Requires-Python: >=3.10.0,<4.0
Classifier: Development Status :: 3 - Alpha
Classifier: Intended Audience :: Developers
Classifier: Intended Audience :: Science/Research
Classifier: License :: OSI Approved :: MIT License
Classifier: Programming Language :: Python :: 3
Classifier: Programming Language :: Python :: 3.10
Classifier: Programming Language :: Python :: 3.11
Classifier: Programming Language :: Python :: 3.12
Classifier: Programming Language :: Python :: 3.13
Classifier: Topic :: Scientific/Engineering :: Artificial Intelligence
Requires-Dist: ipython (>=8.0.0)
Requires-Dist: numpy (==1.24.4)
Requires-Dist: openai (>=1.0.0)
Requires-Dist: pandas (==2.0.3)
Project-URL: Repository, https://github.com/codeastra2/llm-feat
